imcvtP/__init__.py
imcvtP/converter.py
imcvtP-1.0.1.dist-info/LICENSE
imcvtP-1.0.1.dist-info/METADATA
imcvtP-1.0.1.dist-info/WHEEL
imcvtP-1.0.1.dist-info/top_level.txt
imcvtP-1.0.1.dist-info/RECORD
