Metadata-Version: 2.1
Name: imcvtP
Version: 1.0.1
Summary: Test package for distribution
Home-page: 
Download-URL: 
Author: MSRhie
Author-email: stat_12@naver.com
Keywords: GIFCONVERTER,gifconverter
Classifier: Programming Language :: Python :: 3
Classifier: License :: OSI Approved :: MIT License
Classifier: Operating System :: OS Independent
Requires-Python: >=3
License-File: LICENSE
Requires-Dist: pillow
